{
  "paths": [
    {
      "distance": 29421.0,
      "time": 974140,
      "points": {
        "type": "LineString",
        "coordinates": [
          [
            107.16391,
            10.918271
          ],
          [
            107.163801,
            10.91756
          ],
          [
            107.163726,
            10.917182
          ],
          [
            107.163506,
            10.915974
          ],
          [
            107.163218,
            10.914566
          ],
          [
            107.16282,
            10.913314
          ],
          [
            107.162392,
            10.91245
          ],
          [
            107.162018,
            10.911827
          ],
          [
            107.161645,
            10.911282
          ],
          [
            107.161082,
            10.910616
          ],
          [
            107.160342,
            10.909889
          ],
          [
            107.159497,
            10.909195
          ],
          [
            107.150914,
            10.902336
          ],
          [
            107.150293,
            10.901774
          ],
          [
            107.149598,
            10.900996
          ],
          [
            107.149113,
            10.900326
          ],
          [
            107.148633,
            10.899578
          ],
          [
            107.148129,
            10.898613
          ],
          [
            107.147815,
            10.897965
          ],
          [
            107.145352,
            10.892851
          ],
          [
            107.144573,
            10.891426
          ],
          [
            107.14403,
            10.890642
          ],
          [
            107.143551,
            10.890091
          ],
          [
            107.143051,
            10.889585
          ],
          [
            107.142471,
            10.889086
          ],
          [
            107.141014,
            10.888043
          ],
          [
            107.133383,
            10.882924
          ],
          [
            107.131918,
            10.881883
          ],
          [
            107.130557,
            10.88083
          ],
          [
            107.129552,
            10.879994
          ],
          [
            107.128552,
            10.879088
          ],
          [
            107.127663,
            10.878257
          ],
          [
            107.126738,
            10.8773
          ],
          [
            107.124659,
            10.874958
          ],
          [
            107.122909,
            10.872756
          ],
          [
            107.122477,
            10.872203
          ],
          [
            107.113881,
            10.861052
          ],
          [
            107.112962,
            10.859862
          ],
          [
            107.112577,
            10.859365
          ],
          [
            107.110716,
            10.857006
          ],
          [
            107.110246,
            10.85643
          ],
          [
            107.109892,
            10.855977
          ],
          [
            107.108615,
            10.854544
          ],
          [
            107.106495,
            10.852406
          ],
          [
            107.105172,
            10.851181
          ],
          [
            107.104528,
            10.85063
          ],
          [
            107.103674,
            10.849913
          ],
          [
            107.101505,
            10.848196
          ],
          [
            107.100622,
            10.847505
          ],
          [
            107.098956,
            10.846175
          ],
          [
            107.097731,
            10.845187
          ],
          [
            107.095164,
            10.843156
          ],
          [
            107.093791,
            10.842074
          ],
          [
            107.093335,
            10.84171
          ],
          [
            107.093254,
            10.841647
          ],
          [
            107.091597,
            10.840349
          ],
          [
            107.087787,
            10.837326
          ],
          [
            107.085153,
            10.835169
          ],
          [
            107.081705,
            10.832204
          ],
          [
            107.078497,
            10.829299
          ],
          [
            107.074191,
            10.825287
          ],
          [
            107.07075,
            10.822063
          ],
          [
            107.070341,
            10.821681
          ],
          [
            107.058458,
            10.81058
          ],
          [
            107.057953,
            10.810101
          ],
          [
            107.055073,
            10.807416
          ],
          [
            107.052231,
            10.8048
          ],
          [
            107.04993,
            10.802787
          ],
          [
            107.047995,
            10.801215
          ],
          [
            107.046033,
            10.799703
          ],
          [
            107.044308,
            10.79844
          ],
          [
            107.042527,
            10.797193
          ],
          [
            107.040311,
            10.795735
          ],
          [
            107.038057,
            10.794324
          ],
          [
            107.029345,
            10.788976
          ],
          [
            107.013277,
            10.779113
          ],
          [
            107.010753,
            10.777579
          ],
          [
            107.00905,
            10.776587
          ],
          [
            107.009046,
            10.776587
          ],
          [
            107.007491,
            10.775767
          ],
          [
            107.005833,
            10.774992
          ],
          [
            107.0049,
            10.774601
          ],
          [
            107.00408,
            10.774278
          ],
          [
            107.003205,
            10.773958
          ],
          [
            107.002283,
            10.773654
          ],
          [
            107.001252,
            10.773338
          ],
          [
            106.999671,
            10.772923
          ],
          [
            106.997396,
            10.772426
          ],
          [
            106.991464,
            10.771184
          ],
          [
            106.987933,
            10.770445
          ],
          [
            106.987745,
            10.770406
          ],
          [
            106.981483,
            10.769095
          ],
          [
            106.978767,
            10.768523
          ],
          [
            106.976046,
            10.768062
          ],
          [
            106.971528,
            10.767085
          ],
          [
            106.969771,
            10.766738
          ],
          [
            106.967423,
            10.766238
          ],
          [
            106.966889,
            10.7663
          ],
          [
            106.966011,
            10.766128
          ],
          [
            106.96513,
            10.765947
          ],
          [
            106.964921,
            10.765905
          ],
          [
            106.964618,
            10.765854
          ],
          [
            106.96442,
            10.765823
          ],
          [
            106.96251,
            10.765699
          ],
          [
            106.961822,
            10.765662
          ],
          [
            106.961724,
            10.76566
          ],
          [
            106.961634,
            10.765654
          ],
          [
            106.961268,
            10.765633
          ],
          [
            106.960904,
            10.765625
          ],
          [
            106.960396,
            10.765625
          ],
          [
            106.960181,
            10.76563
          ],
          [
            106.959968,
            10.765671
          ],
          [
            106.959745,
            10.765754
          ],
          [
            106.959462,
            10.765974
          ],
          [
            106.959345,
            10.766001
          ],
          [
            106.959292,
            10.766008
          ],
          [
            106.959238,
            10.766006
          ],
          [
            106.959179,
            10.765995
          ],
          [
            106.959124,
            10.765974
          ],
          [
            106.95909,
            10.765955
          ],
          [
            106.958796,
            10.765713
          ],
          [
            106.958702,
            10.765683
          ],
          [
            106.958616,
            10.765657
          ],
          [
            106.958514,
            10.76565
          ],
          [
            106.958062,
            10.765669
          ],
          [
            106.957656,
            10.765688
          ],
          [
            106.957062,
            10.765742
          ],
          [
            106.956551,
            10.765777
          ],
          [
            106.956462,
            10.765786
          ],
          [
            106.956462,
            10.765786
          ]
        ]
      }
    }
  ]
}