{
  "paths": [
    {
      "distance": 50787.0,
      "time": 1947599,
      "points": {
        "type": "LineString",
        "coordinates": [
          [
            105.907722,
            20.774058
          ],
          [
            105.907014,
            20.775038
          ],
          [
            105.906155,
            20.776174
          ],
          [
            105.904824,
            20.778192
          ],
          [
            105.903095,
            20.780848
          ],
          [
            105.902876,
            20.781214
          ],
          [
            105.902339,
            20.782113
          ],
          [
            105.901619,
            20.783415
          ],
          [
            105.900761,
            20.78518
          ],
          [
            105.90027,
            20.786367
          ],
          [
            105.900001,
            20.787027
          ],
          [
            105.899403,
            20.788721
          ],
          [
            105.899049,
            20.789868
          ],
          [
            105.898165,
            20.792935
          ],
          [
            105.897414,
            20.795502
          ],
          [
            105.897066,
            20.79659
          ],
          [
            105.896716,
            20.797527
          ],
          [
            105.896048,
            20.799191
          ],
          [
            105.895347,
            20.800676
          ],
          [
            105.89413,
            20.803123
          ],
          [
            105.89277,
            20.805769
          ],
          [
            105.892339,
            20.806675
          ],
          [
            105.891732,
            20.808145
          ],
          [
            105.89125,
            20.809597
          ],
          [
            105.890863,
            20.811016
          ],
          [
            105.890588,
            20.81235
          ],
          [
            105.890422,
            20.813516
          ],
          [
            105.890201,
            20.815092
          ],
          [
            105.889747,
            20.818348
          ],
          [
            105.889161,
            20.822429
          ],
          [
            105.888896,
            20.824242
          ],
          [
            105.888591,
            20.826484
          ],
          [
            105.888005,
            20.830575
          ],
          [
            105.887792,
            20.832065
          ],
          [
            105.887418,
            20.834757
          ],
          [
            105.886284,
            20.842773
          ],
          [
            105.885969,
            20.84502
          ],
          [
            105.885831,
            20.845779
          ],
          [
            105.885626,
            20.846698
          ],
          [
            105.885349,
            20.847688
          ],
          [
            105.884906,
            20.848933
          ],
          [
            105.884205,
            20.85077
          ],
          [
            105.883674,
            20.852124
          ],
          [
            105.883106,
            20.853641
          ],
          [
            105.882134,
            20.856212
          ],
          [
            105.881664,
            20.857602
          ],
          [
            105.881508,
            20.858191
          ],
          [
            105.881368,
            20.858751
          ],
          [
            105.881259,
            20.859348
          ],
          [
            105.881201,
            20.859666
          ],
          [
            105.881049,
            20.860697
          ],
          [
            105.880989,
            20.861456
          ],
          [
            105.88097,
            20.862405
          ],
          [
            105.880977,
            20.863051
          ],
          [
            105.881028,
            20.863955
          ],
          [
            105.881092,
            20.865308
          ],
          [
            105.881101,
            20.865513
          ],
          [
            105.881099,
            20.866495
          ],
          [
            105.881004,
            20.867329
          ],
          [
            105.880911,
            20.867843
          ],
          [
            105.880887,
            20.868136
          ],
          [
            105.880908,
            20.86827
          ],
          [
            105.880946,
            20.868376
          ],
          [
            105.880999,
            20.868431
          ],
          [
            105.881109,
            20.868478
          ],
          [
            105.881252,
            20.868507
          ],
          [
            105.881344,
            20.868539
          ],
          [
            105.881469,
            20.868588
          ],
          [
            105.881606,
            20.868644
          ],
          [
            105.8817,
            20.868717
          ],
          [
            105.881772,
            20.868791
          ],
          [
            105.881885,
            20.868891
          ],
          [
            105.881958,
            20.86897
          ],
          [
            105.881982,
            20.86906
          ],
          [
            105.882037,
            20.869163
          ],
          [
            105.882073,
            20.869253
          ],
          [
            105.882108,
            20.869341
          ],
          [
            105.882142,
            20.869426
          ],
          [
            105.882204,
            20.869584
          ],
          [
            105.88225,
            20.86974
          ],
          [
            105.882001,
            20.8698
          ],
          [
            105.881469,
            20.869898
          ],
          [
            105.880893,
            20.870004
          ],
          [
            105.879922,
            20.87023
          ],
          [
            105.87811,
            20.870584
          ],
          [
            105.878009,
            20.870601
          ],
          [
            105.877943,
            20.870614
          ],
          [
            105.877835,
            20.870631
          ],
          [
            105.877721,
            20.870648
          ],
          [
            105.87756,
            20.870669
          ],
          [
            105.877416,
            20.870689
          ],
          [
            105.877137,
            20.870721
          ],
          [
            105.877158,
            20.870886
          ],
          [
            105.877161,
            20.870911
          ],
          [
            105.877184,
            20.87115
          ],
          [
            105.877203,
            20.871325
          ],
          [
            105.877233,
            20.871455
          ],
          [
            105.877283,
            20.871587
          ],
          [
            105.877343,
            20.871631
          ],
          [
            105.877441,
            20.871746
          ],
          [
            105.877537,
            20.871862
          ],
          [
            105.877568,
            20.8719
          ],
          [
            105.87769,
            20.872032
          ],
          [
            105.877808,
            20.872155
          ],
          [
            105.877911,
            20.872225
          ],
          [
            105.878012,
            20.872253
          ],
          [
            105.878119,
            20.872257
          ],
          [
            105.878246,
            20.872233
          ],
          [
            105.87834,
            20.872179
          ],
          [
            105.878429,
            20.872092
          ],
          [
            105.878536,
            20.871974
          ],
          [
            105.878721,
            20.871703
          ],
          [
            105.879187,
            20.871208
          ],
          [
            105.879689,
            20.870432
          ],
          [
            105.880183,
            20.869487
          ],
          [
            105.880435,
            20.868872
          ],
          [
            105.880603,
            20.868352
          ],
          [
            105.880748,
            20.867827
          ],
          [
            105.880847,
            20.8673
          ],
          [
            105.880853,
            20.867237
          ],
          [
            105.880925,
            20.866482
          ],
          [
            105.880942,
            20.865512
          ],
          [
            105.880863,
            20.863883
          ],
          [
            105.880819,
            20.863072
          ],
          [
            105.880799,
            20.862403
          ],
          [
            105.880742,
            20.861469
          ],
          [
            105.880803,
            20.860684
          ],
          [
            105.880952,
            20.859657
          ],
          [
            105.880956,
            20.859619
          ],
          [
            105.881139,
            20.858707
          ],
          [
            105.881276,
            20.858136
          ],
          [
            105.881336,
            20.857913
          ],
          [
            105.881443,
            20.857523
          ],
          [
            105.881605,
            20.857033
          ],
          [
            105.881897,
            20.856147
          ],
          [
            105.882208,
            20.855344
          ],
          [
            105.882534,
            20.854501
          ],
          [
            105.882896,
            20.853566
          ],
          [
            105.883461,
            20.852035
          ],
          [
            105.88397,
            20.850688
          ],
          [
            105.884678,
            20.848868
          ],
          [
            105.885125,
            20.847628
          ],
          [
            105.885414,
            20.846632
          ],
          [
            105.885608,
            20.845728
          ],
          [
            105.885743,
            20.844972
          ],
          [
            105.88606,
            20.842754
          ],
          [
            105.887193,
            20.834699
          ],
          [
            105.887563,
            20.832072
          ],
          [
            105.887787,
            20.830552
          ],
          [
            105.888354,
            20.826478
          ],
          [
            105.888483,
            20.825548
          ],
          [
            105.888676,
            20.824213
          ],
          [
            105.88894,
            20.822431
          ],
          [
            105.889519,
            20.818358
          ],
          [
            105.889977,
            20.815076
          ],
          [
            105.890197,
            20.813513
          ],
          [
            105.890384,
            20.812317
          ],
          [
            105.890661,
            20.810974
          ],
          [
            105.891051,
            20.809563
          ],
          [
            105.891543,
            20.808096
          ],
          [
            105.892163,
            20.806609
          ],
          [
            105.892571,
            20.805698
          ],
          [
            105.893907,
            20.803042
          ],
          [
            105.895149,
            20.800605
          ],
          [
            105.895851,
            20.799133
          ],
          [
            105.896516,
            20.79746
          ],
          [
            105.896855,
            20.796548
          ],
          [
            105.897226,
            20.795376
          ],
          [
            105.897929,
            20.792886
          ],
          [
            105.898824,
            20.789846
          ],
          [
            105.899177,
            20.788671
          ],
          [
            105.899778,
            20.786961
          ],
          [
            105.900033,
            20.786298
          ],
          [
            105.900528,
            20.785132
          ],
          [
            105.901375,
            20.78337
          ],
          [
            105.902108,
            20.782021
          ],
          [
            105.902144,
            20.781961
          ],
          [
            105.902886,
            20.780731
          ],
          [
            105.90479,
            20.77781
          ],
          [
            105.906071,
            20.775913
          ],
          [
            105.907715,
            20.773432
          ],
          [
            105.908543,
            20.772155
          ],
          [
            105.909635,
            20.770481
          ],
          [
            105.911783,
            20.767275
          ],
          [
            105.911855,
            20.767167
          ],
          [
            105.912309,
            20.766469
          ],
          [
            105.912543,
            20.766111
          ],
          [
            105.91401,
            20.763858
          ],
          [
            105.915097,
            20.762066
          ],
          [
            105.916293,
            20.759857
          ],
          [
            105.917408,
            20.757374
          ],
          [
            105.91821,
            20.755398
          ],
          [
            105.918821,
            20.753372
          ],
          [
            105.919448,
            20.75092
          ],
          [
            105.919863,
            20.748758
          ],
          [
            105.920127,
            20.746812
          ],
          [
            105.920278,
            20.745004
          ],
          [
            105.920338,
            20.743587
          ],
          [
            105.920358,
            20.742269
          ],
          [
            105.920318,
            20.740896
          ],
          [
            105.920227,
            20.739555
          ],
          [
            105.920109,
            20.738295
          ],
          [
            105.91986,
            20.736599
          ],
          [
            105.919431,
            20.734357
          ],
          [
            105.918777,
            20.731679
          ],
          [
            105.91835,
            20.729946
          ],
          [
            105.918171,
            20.728935
          ],
          [
            105.918067,
            20.728122
          ],
          [
            105.917964,
            20.727146
          ],
          [
            105.917882,
            20.7259
          ],
          [
            105.917874,
            20.724712
          ],
          [
            105.917899,
            20.723475
          ],
          [
            105.918142,
            20.720665
          ],
          [
            105.918162,
            20.720502
          ],
          [
            105.918279,
            20.719388
          ],
          [
            105.918384,
            20.717811
          ],
          [
            105.918407,
            20.715213
          ],
          [
            105.918425,
            20.713287
          ],
          [
            105.918439,
            20.711924
          ],
          [
            105.918493,
            20.711024
          ],
          [
            105.918501,
            20.710205
          ],
          [
            105.918534,
            20.707281
          ],
          [
            105.918548,
            20.706709
          ],
          [
            105.918589,
            20.706031
          ],
          [
            105.91865,
            20.70503
          ],
          [
            105.918816,
            20.703999
          ],
          [
            105.919019,
            20.703047
          ],
          [
            105.919199,
            20.702369
          ],
          [
            105.919343,
            20.701855
          ],
          [
            105.919708,
            20.700782
          ],
          [
            105.920065,
            20.699965
          ],
          [
            105.920431,
            20.699215
          ],
          [
            105.920881,
            20.698364
          ],
          [
            105.921381,
            20.69757
          ],
          [
            105.922112,
            20.696523
          ],
          [
            105.923944,
            20.694047
          ],
          [
            105.925929,
            20.69141
          ],
          [
            105.927252,
            20.689624
          ],
          [
            105.929215,
            20.687031
          ],
          [
            105.930638,
            20.685146
          ],
          [
            105.932134,
            20.683128
          ],
          [
            105.933099,
            20.681808
          ],
          [
            105.933396,
            20.681282
          ],
          [
            105.933946,
            20.680369
          ],
          [
            105.934496,
            20.679278
          ],
          [
            105.934749,
            20.678887
          ],
          [
            105.935289,
            20.677613
          ],
          [
            105.935888,
            20.675729
          ],
          [
            105.936171,
            20.674363
          ],
          [
            105.936331,
            20.673384
          ],
          [
            105.936406,
            20.672636
          ],
          [
            105.936457,
            20.671835
          ],
          [
            105.936481,
            20.669956
          ],
          [
            105.936453,
            20.666165
          ],
          [
            105.936436,
            20.660719
          ],
          [
            105.936513,
            20.658054
          ],
          [
            105.936703,
            20.655671
          ],
          [
            105.936812,
            20.654662
          ],
          [
            105.937231,
            20.651994
          ],
          [
            105.937437,
            20.650633
          ],
          [
            105.938153,
            20.64767
          ],
          [
            105.938665,
            20.645635
          ],
          [
            105.939451,
            20.642469
          ],
          [
            105.93961,
            20.641894
          ],
          [
            105.940105,
            20.639968
          ],
          [
            105.940855,
            20.637037
          ],
          [
            105.941729,
            20.633488
          ],
          [
            105.943939,
            20.624617
          ],
          [
            105.945626,
            20.617919
          ],
          [
            105.94598,
            20.616525
          ],
          [
            105.946509,
            20.614377
          ],
          [
            105.947107,
            20.611886
          ],
          [
            105.94744,
            20.610272
          ],
          [
            105.947679,
            20.609028
          ],
          [
            105.947863,
            20.607867
          ],
          [
            105.948033,
            20.606647
          ],
          [
            105.948271,
            20.604598
          ],
          [
            105.94844,
            20.60259
          ],
          [
            105.949153,
            20.594896
          ],
          [
            105.949394,
            20.592538
          ],
          [
            105.949657,
            20.589433
          ],
          [
            105.950211,
            20.58367
          ],
          [
            105.950635,
            20.578959
          ],
          [
            105.950708,
            20.578024
          ],
          [
            105.950981,
            20.575221
          ],
          [
            105.951193,
            20.57277
          ],
          [
            105.951215,
            20.571685
          ],
          [
            105.9512,
            20.570187
          ],
          [
            105.950988,
            20.568512
          ],
          [
            105.950737,
            20.567055
          ],
          [
            105.950268,
            20.56497
          ],
          [
            105.949484,
            20.561537
          ],
          [
            105.949182,
            20.560002
          ],
          [
            105.948952,
            20.558638
          ],
          [
            105.948767,
            20.556796
          ],
          [
            105.948645,
            20.555118
          ],
          [
            105.948417,
            20.551141
          ],
          [
            105.948356,
            20.550161
          ],
          [
            105.948228,
            20.548555
          ],
          [
            105.948213,
            20.548306
          ],
          [
            105.948151,
            20.546958
          ],
          [
            105.947965,
            20.544087
          ],
          [
            105.947928,
            20.543595
          ],
          [
            105.947757,
            20.542279
          ],
          [
            105.947587,
            20.541181
          ],
          [
            105.947569,
            20.540737
          ],
          [
            105.947577,
            20.540009
          ],
          [
            105.947591,
            20.539379
          ],
          [
            105.947514,
            20.539292
          ],
          [
            105.947455,
            20.539146
          ],
          [
            105.947449,
            20.538991
          ],
          [
            105.947496,
            20.538841
          ],
          [
            105.947592,
            20.538714
          ],
          [
            105.947606,
            20.538704
          ],
          [
            105.947621,
            20.538493
          ],
          [
            105.947628,
            20.538363
          ],
          [
            105.947647,
            20.538031
          ]
        ]
      }
    }
  ]
}