{
  "paths": [
    {
      "distance": 101888.0,
      "time": 3373671,
      "points": {
        "type": "LineString",
        "coordinates": [
          [
            105.669186,
            21.279228
          ],
          [
            105.669419,
            21.279065
          ],
          [
            105.669854,
            21.278858
          ],
          [
            105.669942,
            21.278798
          ],
          [
            105.670317,
            21.27854
          ],
          [
            105.670427,
            21.278476
          ],
          [
            105.670534,
            21.278424
          ],
          [
            105.670638,
            21.278379
          ],
          [
            105.670778,
            21.278334
          ],
          [
            105.670898,
            21.278306
          ],
          [
            105.671053,
            21.278284
          ],
          [
            105.671333,
            21.278277
          ],
          [
            105.671491,
            21.278298
          ],
          [
            105.671623,
            21.278327
          ],
          [
            105.671827,
            21.278384
          ],
          [
            105.672058,
            21.278462
          ],
          [
            105.672175,
            21.278486
          ],
          [
            105.672382,
            21.278508
          ],
          [
            105.672566,
            21.278507
          ],
          [
            105.672752,
            21.278481
          ],
          [
            105.672846,
            21.278481
          ],
          [
            105.672911,
            21.27852
          ],
          [
            105.672941,
            21.278558
          ],
          [
            105.672961,
            21.278621
          ],
          [
            105.672967,
            21.278686
          ],
          [
            105.672933,
            21.278797
          ],
          [
            105.672893,
            21.278884
          ],
          [
            105.67285,
            21.278938
          ],
          [
            105.672786,
            21.278975
          ],
          [
            105.672741,
            21.278988
          ],
          [
            105.672699,
            21.278984
          ],
          [
            105.672638,
            21.278967
          ],
          [
            105.672436,
            21.278752
          ],
          [
            105.672244,
            21.278605
          ],
          [
            105.672088,
            21.278538
          ],
          [
            105.671899,
            21.278475
          ],
          [
            105.671699,
            21.278414
          ],
          [
            105.671461,
            21.278356
          ],
          [
            105.671239,
            21.278338
          ],
          [
            105.671034,
            21.278347
          ],
          [
            105.670874,
            21.278374
          ],
          [
            105.670737,
            21.278411
          ],
          [
            105.67059,
            21.278465
          ],
          [
            105.67044,
            21.278538
          ],
          [
            105.670316,
            21.278614
          ],
          [
            105.669984,
            21.27885
          ],
          [
            105.669875,
            21.278928
          ],
          [
            105.669559,
            21.279236
          ],
          [
            105.669316,
            21.279407
          ],
          [
            105.669043,
            21.2796
          ],
          [
            105.668603,
            21.279809
          ],
          [
            105.668377,
            21.279964
          ],
          [
            105.66779,
            21.280384
          ],
          [
            105.667607,
            21.280545
          ],
          [
            105.667464,
            21.280719
          ],
          [
            105.667369,
            21.280892
          ],
          [
            105.667301,
            21.281083
          ],
          [
            105.667258,
            21.281251
          ],
          [
            105.667242,
            21.281412
          ],
          [
            105.667262,
            21.281591
          ],
          [
            105.667307,
            21.281792
          ],
          [
            105.667389,
            21.282009
          ],
          [
            105.667493,
            21.282189
          ],
          [
            105.667718,
            21.28248
          ],
          [
            105.668646,
            21.283645
          ],
          [
            105.668755,
            21.28378
          ],
          [
            105.66884,
            21.283854
          ],
          [
            105.668918,
            21.283907
          ],
          [
            105.669029,
            21.283965
          ],
          [
            105.669144,
            21.283996
          ],
          [
            105.669281,
            21.284003
          ],
          [
            105.669406,
            21.283981
          ],
          [
            105.669539,
            21.283928
          ],
          [
            105.669644,
            21.283848
          ],
          [
            105.66972,
            21.283768
          ],
          [
            105.669773,
            21.283663
          ],
          [
            105.669807,
            21.283567
          ],
          [
            105.669821,
            21.283439
          ],
          [
            105.669807,
            21.283323
          ],
          [
            105.669763,
            21.283219
          ],
          [
            105.66969,
            21.283116
          ],
          [
            105.669595,
            21.28303
          ],
          [
            105.66946,
            21.282956
          ],
          [
            105.669311,
            21.282923
          ],
          [
            105.669136,
            21.282927
          ],
          [
            105.668997,
            21.282953
          ],
          [
            105.66883,
            21.283016
          ],
          [
            105.668671,
            21.283096
          ],
          [
            105.66692,
            21.28423
          ],
          [
            105.665734,
            21.285041
          ],
          [
            105.664686,
            21.285805
          ],
          [
            105.663934,
            21.286396
          ],
          [
            105.663379,
            21.286893
          ],
          [
            105.662938,
            21.287333
          ],
          [
            105.662412,
            21.287905
          ],
          [
            105.661947,
            21.288492
          ],
          [
            105.661428,
            21.289196
          ],
          [
            105.661004,
            21.2899
          ],
          [
            105.660351,
            21.291122
          ],
          [
            105.66026,
            21.291291
          ],
          [
            105.658703,
            21.294201
          ],
          [
            105.657415,
            21.296666
          ],
          [
            105.656359,
            21.298634
          ],
          [
            105.655642,
            21.300009
          ],
          [
            105.654859,
            21.301502
          ],
          [
            105.654489,
            21.302244
          ],
          [
            105.654279,
            21.302665
          ],
          [
            105.654073,
            21.30309
          ],
          [
            105.653749,
            21.303728
          ],
          [
            105.65326,
            21.304757
          ],
          [
            105.653193,
            21.304897
          ],
          [
            105.652891,
            21.305516
          ],
          [
            105.652701,
            21.305899
          ],
          [
            105.652375,
            21.306557
          ],
          [
            105.651543,
            21.308273
          ],
          [
            105.651172,
            21.309099
          ],
          [
            105.650738,
            21.310191
          ],
          [
            105.650367,
            21.311235
          ],
          [
            105.650071,
            21.312211
          ],
          [
            105.649672,
            21.313701
          ],
          [
            105.649301,
            21.314949
          ],
          [
            105.649036,
            21.315737
          ],
          [
            105.64874,
            21.316519
          ],
          [
            105.648322,
            21.317557
          ],
          [
            105.64823,
            21.317772
          ],
          [
            105.648134,
            21.317985
          ],
          [
            105.648039,
            21.318193
          ],
          [
            105.647937,
            21.318398
          ],
          [
            105.647799,
            21.318682
          ],
          [
            105.647693,
            21.318888
          ],
          [
            105.647589,
            21.319093
          ],
          [
            105.647479,
            21.319294
          ],
          [
            105.647372,
            21.319499
          ],
          [
            105.646687,
            21.320624
          ],
          [
            105.646092,
            21.321539
          ],
          [
            105.645539,
            21.322346
          ],
          [
            105.64492,
            21.323164
          ],
          [
            105.644791,
            21.323321
          ],
          [
            105.644713,
            21.323416
          ],
          [
            105.644315,
            21.323904
          ],
          [
            105.643804,
            21.324484
          ],
          [
            105.643153,
            21.3252
          ],
          [
            105.642034,
            21.326336
          ],
          [
            105.640488,
            21.327907
          ],
          [
            105.639619,
            21.328791
          ],
          [
            105.638298,
            21.330121
          ],
          [
            105.637177,
            21.331258
          ],
          [
            105.635767,
            21.332694
          ],
          [
            105.635445,
            21.333018
          ],
          [
            105.633489,
            21.335003
          ],
          [
            105.63197,
            21.336557
          ],
          [
            105.630749,
            21.337793
          ],
          [
            105.630513,
            21.338027
          ],
          [
            105.628993,
            21.339574
          ],
          [
            105.628486,
            21.340102
          ],
          [
            105.627033,
            21.341576
          ],
          [
            105.626907,
            21.341702
          ],
          [
            105.626827,
            21.341782
          ],
          [
            105.626649,
            21.341959
          ],
          [
            105.626617,
            21.341992
          ],
          [
            105.626398,
            21.342212
          ],
          [
            105.623934,
            21.344762
          ],
          [
            105.62313,
            21.345585
          ],
          [
            105.620679,
            21.348051
          ],
          [
            105.620291,
            21.348465
          ],
          [
            105.6196,
            21.349164
          ],
          [
            105.618996,
            21.349725
          ],
          [
            105.618937,
            21.349779
          ],
          [
            105.618303,
            21.350336
          ],
          [
            105.617678,
            21.35083
          ],
          [
            105.617514,
            21.350955
          ],
          [
            105.616945,
            21.351386
          ],
          [
            105.616658,
            21.351596
          ],
          [
            105.615914,
            21.352077
          ],
          [
            105.615188,
            21.352492
          ],
          [
            105.615003,
            21.352597
          ],
          [
            105.614414,
            21.352898
          ],
          [
            105.613824,
            21.353198
          ],
          [
            105.612837,
            21.35362
          ],
          [
            105.611814,
            21.353997
          ],
          [
            105.611309,
            21.354156
          ],
          [
            105.610867,
            21.354296
          ],
          [
            105.609903,
            21.354586
          ],
          [
            105.608893,
            21.354894
          ],
          [
            105.60797,
            21.355193
          ],
          [
            105.607879,
            21.355228
          ],
          [
            105.607176,
            21.355498
          ],
          [
            105.606703,
            21.355705
          ],
          [
            105.605958,
            21.356037
          ],
          [
            105.604351,
            21.356739
          ],
          [
            105.603432,
            21.357112
          ],
          [
            105.602965,
            21.35729
          ],
          [
            105.602278,
            21.357511
          ],
          [
            105.601742,
            21.357668
          ],
          [
            105.601635,
            21.357699
          ],
          [
            105.601053,
            21.357844
          ],
          [
            105.599617,
            21.358156
          ],
          [
            105.598839,
            21.358272
          ],
          [
            105.598401,
            21.358311
          ],
          [
            105.597943,
            21.35837
          ],
          [
            105.596844,
            21.358421
          ],
          [
            105.596015,
            21.358421
          ],
          [
            105.595317,
            21.358407
          ],
          [
            105.594101,
            21.358331
          ],
          [
            105.593287,
            21.358208
          ],
          [
            105.592712,
            21.358124
          ],
          [
            105.592631,
            21.358108
          ],
          [
            105.591909,
            21.357963
          ],
          [
            105.59057,
            21.357653
          ],
          [
            105.589758,
            21.357449
          ],
          [
            105.588747,
            21.357195
          ],
          [
            105.588703,
            21.357184
          ],
          [
            105.588105,
            21.357053
          ],
          [
            105.587464,
            21.356968
          ],
          [
            105.587115,
            21.356921
          ],
          [
            105.587013,
            21.356913
          ],
          [
            105.586507,
            21.356876
          ],
          [
            105.58625,
            21.356856
          ],
          [
            105.585554,
            21.356834
          ],
          [
            105.584573,
            21.356855
          ],
          [
            105.584094,
            21.356894
          ],
          [
            105.583814,
            21.356917
          ],
          [
            105.583604,
            21.356942
          ],
          [
            105.582252,
            21.357104
          ],
          [
            105.579954,
            21.357391
          ],
          [
            105.579821,
            21.357408
          ],
          [
            105.579664,
            21.357429
          ],
          [
            105.579506,
            21.35745
          ],
          [
            105.577945,
            21.357635
          ],
          [
            105.576329,
            21.357837
          ],
          [
            105.573835,
            21.358136
          ],
          [
            105.571965,
            21.358365
          ],
          [
            105.569172,
            21.358697
          ],
          [
            105.567294,
            21.358923
          ],
          [
            105.56682,
            21.35899
          ],
          [
            105.566067,
            21.359127
          ],
          [
            105.565179,
            21.359322
          ],
          [
            105.564555,
            21.359507
          ],
          [
            105.563842,
            21.359743
          ],
          [
            105.563186,
            21.359993
          ],
          [
            105.562598,
            21.360278
          ],
          [
            105.561755,
            21.360708
          ],
          [
            105.561054,
            21.361104
          ],
          [
            105.559563,
            21.362068
          ],
          [
            105.558389,
            21.362745
          ],
          [
            105.557327,
            21.363257
          ],
          [
            105.556507,
            21.363559
          ],
          [
            105.555348,
            21.363924
          ],
          [
            105.554376,
            21.364139
          ],
          [
            105.553594,
            21.364289
          ],
          [
            105.552855,
            21.364379
          ],
          [
            105.551781,
            21.364429
          ],
          [
            105.551404,
            21.36443
          ],
          [
            105.550089,
            21.364398
          ],
          [
            105.549858,
            21.364388
          ],
          [
            105.549226,
            21.364342
          ],
          [
            105.54843,
            21.364264
          ],
          [
            105.54793,
            21.364199
          ],
          [
            105.547392,
            21.36411
          ],
          [
            105.546669,
            21.363975
          ],
          [
            105.545443,
            21.363708
          ],
          [
            105.544696,
            21.363515
          ],
          [
            105.543997,
            21.363315
          ],
          [
            105.54313,
            21.363036
          ],
          [
            105.542466,
            21.362793
          ],
          [
            105.541627,
            21.362456
          ],
          [
            105.540773,
            21.362075
          ],
          [
            105.539447,
            21.361358
          ],
          [
            105.538789,
            21.360961
          ],
          [
            105.537795,
            21.360312
          ],
          [
            105.536685,
            21.359504
          ],
          [
            105.535332,
            21.358411
          ],
          [
            105.534024,
            21.357278
          ],
          [
            105.533581,
            21.356919
          ],
          [
            105.533429,
            21.356796
          ],
          [
            105.533052,
            21.35649
          ],
          [
            105.532839,
            21.356342
          ],
          [
            105.532539,
            21.356134
          ],
          [
            105.53248,
            21.356092
          ],
          [
            105.531885,
            21.35572
          ],
          [
            105.531531,
            21.355521
          ],
          [
            105.531025,
            21.355269
          ],
          [
            105.53055,
            21.35506
          ],
          [
            105.53002,
            21.35486
          ],
          [
            105.529058,
            21.354587
          ],
          [
            105.528281,
            21.354443
          ],
          [
            105.527511,
            21.354355
          ],
          [
            105.526472,
            21.354314
          ],
          [
            105.525497,
            21.354316
          ],
          [
            105.524206,
            21.354362
          ],
          [
            105.521869,
            21.354447
          ],
          [
            105.521631,
            21.354455
          ],
          [
            105.520419,
            21.354486
          ],
          [
            105.516819,
            21.354642
          ],
          [
            105.515433,
            21.354692
          ],
          [
            105.5138,
            21.354739
          ],
          [
            105.510936,
            21.354884
          ],
          [
            105.50953,
            21.354994
          ],
          [
            105.509466,
            21.355
          ],
          [
            105.506809,
            21.355299
          ],
          [
            105.504594,
            21.355571
          ],
          [
            105.502581,
            21.355802
          ],
          [
            105.500636,
            21.356006
          ],
          [
            105.497125,
            21.356233
          ],
          [
            105.494967,
            21.356329
          ],
          [
            105.492154,
            21.35638
          ],
          [
            105.488525,
            21.356456
          ],
          [
            105.488124,
            21.356462
          ],
          [
            105.484404,
            21.356513
          ],
          [
            105.480803,
            21.356563
          ],
          [
            105.47938,
            21.356581
          ],
          [
            105.477957,
            21.356599
          ],
          [
            105.477365,
            21.356607
          ],
          [
            105.474272,
            21.356748
          ],
          [
            105.468928,
            21.356953
          ],
          [
            105.466776,
            21.357017
          ],
          [
            105.464864,
            21.357123
          ],
          [
            105.464726,
            21.357125
          ],
          [
            105.463289,
            21.357148
          ],
          [
            105.460673,
            21.357233
          ],
          [
            105.460178,
            21.357241
          ],
          [
            105.457281,
            21.357344
          ],
          [
            105.45528,
            21.357436
          ],
          [
            105.45481,
            21.357447
          ],
          [
            105.454304,
            21.357476
          ],
          [
            105.452348,
            21.357542
          ],
          [
            105.451871,
            21.357559
          ],
          [
            105.451397,
            21.357588
          ],
          [
            105.450081,
            21.357628
          ],
          [
            105.447354,
            21.357719
          ],
          [
            105.445191,
            21.357817
          ],
          [
            105.442753,
            21.357892
          ],
          [
            105.440464,
            21.357995
          ],
          [
            105.438045,
            21.358098
          ],
          [
            105.437056,
            21.358207
          ],
          [
            105.436066,
            21.358384
          ],
          [
            105.435161,
            21.358593
          ],
          [
            105.434168,
            21.358885
          ],
          [
            105.433401,
            21.359195
          ],
          [
            105.430758,
            21.360198
          ],
          [
            105.429751,
            21.36055
          ],
          [
            105.428598,
            21.360948
          ],
          [
            105.427391,
            21.361355
          ],
          [
            105.425111,
            21.362051
          ],
          [
            105.422944,
            21.362727
          ],
          [
            105.420067,
            21.363607
          ],
          [
            105.416367,
            21.36471
          ],
          [
            105.413229,
            21.365666
          ],
          [
            105.411796,
            21.366072
          ],
          [
            105.410977,
            21.366291
          ],
          [
            105.410145,
            21.366477
          ],
          [
            105.40914,
            21.366642
          ],
          [
            105.408696,
            21.366717
          ],
          [
            105.407733,
            21.366809
          ],
          [
            105.407144,
            21.366856
          ],
          [
            105.406325,
            21.366869
          ],
          [
            105.402791,
            21.366931
          ],
          [
            105.402763,
            21.366931
          ],
          [
            105.401413,
            21.366951
          ],
          [
            105.401339,
            21.366952
          ],
          [
            105.39938,
            21.366982
          ],
          [
            105.395683,
            21.367106
          ],
          [
            105.387128,
            21.367237
          ],
          [
            105.384449,
            21.367216
          ],
          [
            105.383529,
            21.367208
          ],
          [
            105.382359,
            21.367224
          ],
          [
            105.381979,
            21.367225
          ],
          [
            105.381565,
            21.367232
          ],
          [
            105.380763,
            21.367256
          ],
          [
            105.379911,
            21.367298
          ],
          [
            105.379341,
            21.367336
          ],
          [
            105.378975,
            21.367371
          ],
          [
            105.378394,
            21.367443
          ],
          [
            105.378052,
            21.367493
          ],
          [
            105.376833,
            21.367714
          ],
          [
            105.376199,
            21.36788
          ],
          [
            105.375602,
            21.368061
          ],
          [
            105.375118,
            21.368206
          ],
          [
            105.374515,
            21.368394
          ],
          [
            105.373139,
            21.368896
          ],
          [
            105.371852,
            21.369447
          ],
          [
            105.370998,
            21.369832
          ],
          [
            105.37021,
            21.370188
          ],
          [
            105.369436,
            21.370556
          ],
          [
            105.368318,
            21.371147
          ],
          [
            105.36781,
            21.371405
          ],
          [
            105.366719,
            21.372019
          ],
          [
            105.365683,
            21.372638
          ],
          [
            105.364389,
            21.373487
          ],
          [
            105.363716,
            21.373934
          ],
          [
            105.363079,
            21.374372
          ],
          [
            105.361655,
            21.375419
          ],
          [
            105.360348,
            21.376466
          ],
          [
            105.358791,
            21.377874
          ],
          [
            105.35783,
            21.378692
          ],
          [
            105.354504,
            21.381759
          ],
          [
            105.353695,
            21.382575
          ],
          [
            105.352804,
            21.383338
          ],
          [
            105.352127,
            21.383949
          ],
          [
            105.350603,
            21.385388
          ],
          [
            105.348503,
            21.387315
          ],
          [
            105.347651,
            21.387956
          ],
          [
            105.346805,
            21.388583
          ],
          [
            105.346441,
            21.388841
          ],
          [
            105.345607,
            21.389434
          ],
          [
            105.343954,
            21.390403
          ],
          [
            105.34253,
            21.39115
          ],
          [
            105.341323,
            21.391673
          ],
          [
            105.340344,
            21.392096
          ],
          [
            105.339207,
            21.392531
          ],
          [
            105.338428,
            21.392812
          ],
          [
            105.337966,
            21.392927
          ],
          [
            105.337641,
            21.393007
          ],
          [
            105.335765,
            21.393507
          ],
          [
            105.334486,
            21.393776
          ],
          [
            105.332915,
            21.393995
          ],
          [
            105.331757,
            21.394121
          ],
          [
            105.331531,
            21.394146
          ],
          [
            105.331057,
            21.394173
          ],
          [
            105.330594,
            21.394194
          ],
          [
            105.329415,
            21.39423
          ],
          [
            105.328103,
            21.394211
          ],
          [
            105.326956,
            21.39421
          ],
          [
            105.325661,
            21.394216
          ],
          [
            105.324543,
            21.394211
          ],
          [
            105.322647,
            21.394208
          ],
          [
            105.321804,
            21.39421
          ],
          [
            105.321339,
            21.39421
          ],
          [
            105.320875,
            21.394211
          ],
          [
            105.319358,
            21.394183
          ],
          [
            105.319059,
            21.394184
          ],
          [
            105.318783,
            21.394173
          ],
          [
            105.318277,
            21.394154
          ],
          [
            105.3178,
            21.394134
          ],
          [
            105.316486,
            21.394019
          ],
          [
            105.316198,
            21.393977
          ],
          [
            105.31595,
            21.393941
          ],
          [
            105.314866,
            21.393745
          ],
          [
            105.314643,
            21.393707
          ],
          [
            105.314044,
            21.39357
          ],
          [
            105.313509,
            21.393433
          ],
          [
            105.312887,
            21.393254
          ],
          [
            105.312358,
            21.393079
          ],
          [
            105.312039,
            21.392973
          ],
          [
            105.310978,
            21.392666
          ],
          [
            105.31,
            21.39241
          ],
          [
            105.308925,
            21.392195
          ],
          [
            105.30841,
            21.392117
          ],
          [
            105.307897,
            21.392064
          ],
          [
            105.307175,
            21.392015
          ],
          [
            105.306289,
            21.392004
          ],
          [
            105.30544,
            21.392033
          ],
          [
            105.304858,
            21.392112
          ],
          [
            105.303265,
            21.392368
          ],
          [
            105.302661,
            21.392498
          ],
          [
            105.302067,
            21.392665
          ],
          [
            105.301298,
            21.39293
          ],
          [
            105.300716,
            21.393143
          ],
          [
            105.300101,
            21.393424
          ],
          [
            105.299561,
            21.393703
          ],
          [
            105.29803,
            21.394625
          ],
          [
            105.295254,
            21.396516
          ],
          [
            105.293156,
            21.397799
          ],
          [
            105.291765,
            21.398641
          ],
          [
            105.290513,
            21.399353
          ],
          [
            105.289766,
            21.39973
          ],
          [
            105.289599,
            21.399814
          ],
          [
            105.288165,
            21.400468
          ],
          [
            105.286765,
            21.401123
          ],
          [
            105.285177,
            21.401773
          ],
          [
            105.284395,
            21.402053
          ],
          [
            105.283477,
            21.402368
          ],
          [
            105.282441,
            21.40269
          ],
          [
            105.281275,
            21.40299
          ],
          [
            105.280206,
            21.40328
          ],
          [
            105.278916,
            21.403658
          ],
          [
            105.277668,
            21.404052
          ],
          [
            105.277132,
            21.404288
          ],
          [
            105.275635,
            21.404942
          ],
          [
            105.275115,
            21.405171
          ],
          [
            105.273912,
            21.405658
          ],
          [
            105.273204,
            21.406009
          ],
          [
            105.27265,
            21.406233
          ],
          [
            105.272206,
            21.406406
          ],
          [
            105.271252,
            21.406728
          ],
          [
            105.270479,
            21.406995
          ],
          [
            105.269751,
            21.407177
          ],
          [
            105.268912,
            21.407319
          ],
          [
            105.268017,
            21.407493
          ],
          [
            105.265967,
            21.407924
          ],
          [
            105.263894,
            21.408272
          ],
          [
            105.262297,
            21.408606
          ],
          [
            105.259984,
            21.4091
          ],
          [
            105.259186,
            21.409321
          ],
          [
            105.257597,
            21.409817
          ],
          [
            105.254127,
            21.411032
          ],
          [
            105.25347,
            21.411248
          ],
          [
            105.252599,
            21.41149
          ],
          [
            105.251702,
            21.411698
          ],
          [
            105.249902,
            21.412037
          ],
          [
            105.249659,
            21.412077
          ],
          [
            105.247821,
            21.412382
          ],
          [
            105.246786,
            21.412544
          ],
          [
            105.245733,
            21.412697
          ],
          [
            105.244456,
            21.412904
          ],
          [
            105.243151,
            21.413078
          ],
          [
            105.242672,
            21.413159
          ],
          [
            105.242467,
            21.413194
          ],
          [
            105.241492,
            21.413413
          ],
          [
            105.240876,
            21.413596
          ],
          [
            105.240219,
            21.413848
          ],
          [
            105.239582,
            21.414158
          ],
          [
            105.238843,
            21.414564
          ],
          [
            105.238321,
            21.414911
          ],
          [
            105.237867,
            21.415257
          ],
          [
            105.236528,
            21.41635
          ],
          [
            105.236142,
            21.416716
          ],
          [
            105.234137,
            21.418371
          ],
          [
            105.232233,
            21.419884
          ],
          [
            105.231687,
            21.420332
          ],
          [
            105.229799,
            21.42188
          ],
          [
            105.229419,
            21.422191
          ],
          [
            105.226792,
            21.424337
          ],
          [
            105.22637,
            21.424681
          ],
          [
            105.226237,
            21.42479
          ],
          [
            105.222141,
            21.428181
          ],
          [
            105.219926,
            21.429976
          ],
          [
            105.219556,
            21.430283
          ],
          [
            105.212919,
            21.435707
          ],
          [
            105.211917,
            21.436487
          ],
          [
            105.210955,
            21.437154
          ],
          [
            105.210016,
            21.437752
          ],
          [
            105.208955,
            21.438328
          ],
          [
            105.208861,
            21.438372
          ],
          [
            105.20862,
            21.438497
          ],
          [
            105.208164,
            21.438717
          ],
          [
            105.207447,
            21.439054
          ],
          [
            105.204882,
            21.440237
          ],
          [
            105.202546,
            21.441302
          ],
          [
            105.199159,
            21.442887
          ],
          [
            105.196962,
            21.443937
          ],
          [
            105.193443,
            21.445559
          ],
          [
            105.190963,
            21.446673
          ],
          [
            105.19024,
            21.446962
          ],
          [
            105.189826,
            21.447097
          ],
          [
            105.18933,
            21.447261
          ],
          [
            105.188459,
            21.44755
          ],
          [
            105.187215,
            21.447922
          ],
          [
            105.185665,
            21.448276
          ],
          [
            105.184103,
            21.448572
          ],
          [
            105.182939,
            21.448734
          ],
          [
            105.18205,
            21.448826
          ],
          [
            105.179554,
            21.448926
          ],
          [
            105.175463,
            21.448895
          ],
          [
            105.170644,
            21.448828
          ],
          [
            105.170482,
            21.448826
          ],
          [
            105.168202,
            21.448879
          ],
          [
            105.165594,
            21.449104
          ],
          [
            105.163353,
            21.449367
          ],
          [
            105.161174,
            21.44963
          ],
          [
            105.159595,
            21.449769
          ],
          [
            105.155032,
            21.450288
          ],
          [
            105.151629,
            21.450695
          ],
          [
            105.148865,
            21.45103
          ],
          [
            105.147887,
            21.451097
          ],
          [
            105.146847,
            21.451115
          ],
          [
            105.145828,
            21.451064
          ],
          [
            105.145664,
            21.451055
          ],
          [
            105.144529,
            21.450916
          ],
          [
            105.143356,
            21.450667
          ],
          [
            105.142,
            21.450301
          ],
          [
            105.141355,
            21.450037
          ],
          [
            105.140729,
            21.449752
          ],
          [
            105.139722,
            21.449235
          ],
          [
            105.138856,
            21.448771
          ],
          [
            105.138013,
            21.448187
          ],
          [
            105.135915,
            21.446671
          ],
          [
            105.133046,
            21.444699
          ],
          [
            105.131163,
            21.443786
          ],
          [
            105.123405,
            21.440619
          ],
          [
            105.123146,
            21.440546
          ],
          [
            105.122755,
            21.440386
          ],
          [
            105.121773,
            21.440073
          ],
          [
            105.121262,
            21.439934
          ],
          [
            105.120003,
            21.439651
          ],
          [
            105.118721,
            21.439405
          ],
          [
            105.117606,
            21.439257
          ],
          [
            105.116772,
            21.439146
          ],
          [
            105.11586,
            21.439087
          ],
          [
            105.114971,
            21.439059
          ],
          [
            105.114194,
            21.439069
          ],
          [
            105.113331,
            21.439101
          ],
          [
            105.112419,
            21.439156
          ],
          [
            105.11076,
            21.43933
          ],
          [
            105.108455,
            21.439701
          ],
          [
            105.106647,
            21.440033
          ],
          [
            105.105486,
            21.440342
          ],
          [
            105.104664,
            21.440587
          ],
          [
            105.104013,
            21.440827
          ],
          [
            105.103252,
            21.441153
          ],
          [
            105.102716,
            21.441416
          ],
          [
            105.102392,
            21.441542
          ],
          [
            105.098692,
            21.44392
          ],
          [
            105.097551,
            21.444587
          ],
          [
            105.096453,
            21.445168
          ],
          [
            105.095353,
            21.445688
          ],
          [
            105.093134,
            21.446591
          ],
          [
            105.092805,
            21.446724
          ],
          [
            105.092258,
            21.44691
          ],
          [
            105.091315,
            21.447215
          ],
          [
            105.089507,
            21.44781
          ],
          [
            105.087646,
            21.448429
          ],
          [
            105.085814,
            21.449035
          ],
          [
            105.085134,
            21.449293
          ],
          [
            105.084441,
            21.449597
          ],
          [
            105.083437,
            21.450157
          ],
          [
            105.082379,
            21.450893
          ],
          [
            105.081633,
            21.451508
          ],
          [
            105.080851,
            21.452353
          ],
          [
            105.080262,
            21.453063
          ],
          [
            105.075243,
            21.460002
          ],
          [
            105.074856,
            21.46053
          ],
          [
            105.068594,
            21.469327
          ],
          [
            105.066956,
            21.471606
          ],
          [
            105.066237,
            21.472589
          ],
          [
            105.065557,
            21.473413
          ],
          [
            105.065241,
            21.473756
          ],
          [
            105.064648,
            21.474387
          ],
          [
            105.063912,
            21.475123
          ],
          [
            105.062818,
            21.476154
          ],
          [
            105.060648,
            21.478119
          ],
          [
            105.057927,
            21.480507
          ],
          [
            105.055191,
            21.48294
          ],
          [
            105.047996,
            21.489347
          ],
          [
            105.047572,
            21.489719
          ],
          [
            105.046067,
            21.491028
          ],
          [
            105.045483,
            21.491606
          ],
          [
            105.044917,
            21.492156
          ],
          [
            105.04475,
            21.492333
          ],
          [
            105.044286,
            21.492883
          ],
          [
            105.043716,
            21.49362
          ],
          [
            105.043282,
            21.494231
          ],
          [
            105.042904,
            21.494791
          ],
          [
            105.042168,
            21.49594
          ],
          [
            105.041807,
            21.496397
          ],
          [
            105.041445,
            21.496824
          ],
          [
            105.040839,
            21.497458
          ],
          [
            105.040216,
            21.498079
          ],
          [
            105.039573,
            21.498678
          ],
          [
            105.039082,
            21.499159
          ],
          [
            105.038457,
            21.499738
          ],
          [
            105.037327,
            21.500822
          ],
          [
            105.035292,
            21.502732
          ],
          [
            105.033099,
            21.504808
          ],
          [
            105.03115,
            21.506645
          ],
          [
            105.030576,
            21.507138
          ],
          [
            105.030002,
            21.507559
          ],
          [
            105.02906,
            21.508178
          ],
          [
            105.02806,
            21.508682
          ],
          [
            105.027325,
            21.508994
          ],
          [
            105.026588,
            21.509244
          ],
          [
            105.025775,
            21.509456
          ],
          [
            105.025241,
            21.509577
          ],
          [
            105.024573,
            21.509697
          ],
          [
            105.023059,
            21.509949
          ],
          [
            105.022307,
            21.510116
          ],
          [
            105.021784,
            21.510269
          ],
          [
            105.021131,
            21.510508
          ],
          [
            105.019104,
            21.511379
          ],
          [
            105.016196,
            21.512645
          ],
          [
            105.014484,
            21.513415
          ],
          [
            105.009387,
            21.515605
          ],
          [
            105.007163,
            21.516505
          ],
          [
            105.005095,
            21.517415
          ],
          [
            105.003448,
            21.518244
          ],
          [
            105.001873,
            21.51915
          ],
          [
            104.999663,
            21.520572
          ],
          [
            104.998639,
            21.521319
          ],
          [
            104.995572,
            21.523523
          ],
          [
            104.994629,
            21.524146
          ],
          [
            104.992226,
            21.525897
          ],
          [
            104.991502,
            21.526411
          ],
          [
            104.990841,
            21.52686
          ],
          [
            104.990362,
            21.52711
          ],
          [
            104.989818,
            21.527374
          ],
          [
            104.989434,
            21.527561
          ],
          [
            104.988857,
            21.527782
          ],
          [
            104.988551,
            21.527888
          ],
          [
            104.988256,
            21.527978
          ],
          [
            104.987739,
            21.528125
          ],
          [
            104.987189,
            21.528268
          ],
          [
            104.986792,
            21.528362
          ],
          [
            104.986387,
            21.528457
          ],
          [
            104.985738,
            21.528584
          ],
          [
            104.984609,
            21.528832
          ],
          [
            104.984037,
            21.528965
          ],
          [
            104.982955,
            21.529287
          ],
          [
            104.982428,
            21.529488
          ],
          [
            104.981923,
            21.529701
          ],
          [
            104.980716,
            21.530214
          ],
          [
            104.975772,
            21.532315
          ],
          [
            104.973834,
            21.533106
          ],
          [
            104.967306,
            21.535909
          ],
          [
            104.962989,
            21.537763
          ],
          [
            104.951828,
            21.542566
          ],
          [
            104.951079,
            21.54293
          ],
          [
            104.950398,
            21.543306
          ],
          [
            104.949989,
            21.543573
          ],
          [
            104.949088,
            21.544279
          ],
          [
            104.948665,
            21.544675
          ],
          [
            104.948247,
            21.545122
          ],
          [
            104.947942,
            21.545503
          ],
          [
            104.947651,
            21.545924
          ],
          [
            104.947386,
            21.546371
          ],
          [
            104.94715,
            21.546804
          ],
          [
            104.945564,
            21.550313
          ],
          [
            104.945226,
            21.550915
          ],
          [
            104.944835,
            21.55159
          ],
          [
            104.938095,
            21.561401
          ],
          [
            104.936029,
            21.564366
          ],
          [
            104.934224,
            21.567007
          ],
          [
            104.933754,
            21.567667
          ],
          [
            104.933484,
            21.568043
          ],
          [
            104.933352,
            21.568225
          ],
          [
            104.932921,
            21.568912
          ],
          [
            104.932603,
            21.569443
          ],
          [
            104.932447,
            21.569732
          ],
          [
            104.932281,
            21.570084
          ],
          [
            104.931903,
            21.570881
          ],
          [
            104.931573,
            21.571621
          ],
          [
            104.931286,
            21.572283
          ],
          [
            104.931172,
            21.572596
          ],
          [
            104.931139,
            21.572666
          ],
          [
            104.931104,
            21.572727
          ],
          [
            104.931057,
            21.572792
          ],
          [
            104.929908,
            21.57448
          ],
          [
            104.929845,
            21.574558
          ],
          [
            104.92978,
            21.574621
          ],
          [
            104.929718,
            21.574679
          ],
          [
            104.922776,
            21.580083
          ],
          [
            104.922703,
            21.580146
          ],
          [
            104.922625,
            21.580209
          ],
          [
            104.920474,
            21.582259
          ],
          [
            104.92037,
            21.582376
          ],
          [
            104.920276,
            21.582491
          ],
          [
            104.915485,
            21.589559
          ],
          [
            104.915019,
            21.59021
          ],
          [
            104.913519,
            21.592115
          ],
          [
            104.913342,
            21.59232
          ],
          [
            104.911922,
            21.59391
          ],
          [
            104.909327,
            21.596467
          ],
          [
            104.909115,
            21.596642
          ],
          [
            104.905763,
            21.599288
          ],
          [
            104.904341,
            21.600571
          ],
          [
            104.903879,
            21.601066
          ],
          [
            104.903729,
            21.601243
          ],
          [
            104.902814,
            21.602676
          ],
          [
            104.902751,
            21.602775
          ],
          [
            104.901959,
            21.604166
          ],
          [
            104.901854,
            21.604378
          ],
          [
            104.901398,
            21.605542
          ],
          [
            104.901179,
            21.606271
          ],
          [
            104.900897,
            21.60754
          ],
          [
            104.899406,
            21.616292
          ],
          [
            104.898516,
            21.621458
          ],
          [
            104.898011,
            21.624336
          ],
          [
            104.897622,
            21.62644
          ],
          [
            104.897388,
            21.627844
          ],
          [
            104.897275,
            21.628736
          ],
          [
            104.897267,
            21.62945
          ],
          [
            104.897272,
            21.629854
          ],
          [
            104.897274,
            21.631054
          ],
          [
            104.897322,
            21.632575
          ],
          [
            104.897378,
            21.633329
          ],
          [
            104.897413,
            21.633954
          ],
          [
            104.897425,
            21.634244
          ],
          [
            104.897362,
            21.635365
          ],
          [
            104.897158,
            21.636909
          ],
          [
            104.896762,
            21.638346
          ],
          [
            104.896318,
            21.639533
          ],
          [
            104.895544,
            21.640969
          ],
          [
            104.895085,
            21.641698
          ],
          [
            104.894233,
            21.642858
          ],
          [
            104.893847,
            21.643486
          ],
          [
            104.893794,
            21.643578
          ],
          [
            104.893752,
            21.643649
          ],
          [
            104.893071,
            21.644685
          ],
          [
            104.892592,
            21.645571
          ],
          [
            104.892249,
            21.646329
          ],
          [
            104.892211,
            21.646412
          ]
        ]
      }
    }
  ]
}