{
  "paths": [
    {
      "distance": 4105.0,
      "time": 164103,
      "points": {
        "type": "LineString",
        "coordinates": [
          [
            106.966139,
            20.974498
          ],
          [
            106.966577,
            20.975731
          ],
          [
            106.966809,
            20.976381
          ],
          [
            106.967035,
            20.977019
          ],
          [
            106.968103,
            20.980088
          ],
          [
            106.9683,
            20.980639
          ],
          [
            106.968781,
            20.98199
          ],
          [
            106.969047,
            20.982639
          ],
          [
            106.969282,
            20.983179
          ],
          [
            106.969568,
            20.983742
          ],
          [
            106.969927,
            20.984375
          ],
          [
            106.970432,
            20.985128
          ],
          [
            106.97117,
            20.986102
          ],
          [
            106.975334,
            20.991241
          ],
          [
            106.975835,
            20.991858
          ],
          [
            106.976419,
            20.992483
          ],
          [
            106.976652,
            20.992666
          ],
          [
            106.976964,
            20.99284
          ],
          [
            106.977268,
            20.992934
          ],
          [
            106.978028,
            20.993117
          ],
          [
            106.979826,
            20.993556
          ],
          [
            106.979944,
            20.99357
          ],
          [
            106.980049,
            20.993578
          ],
          [
            106.980139,
            20.993584
          ],
          [
            106.98024,
            20.993579
          ],
          [
            106.98036,
            20.993578
          ],
          [
            106.980535,
            20.993565
          ],
          [
            106.981436,
            20.993462
          ],
          [
            106.982019,
            20.993403
          ],
          [
            106.982387,
            20.993385
          ],
          [
            106.982955,
            20.993296
          ],
          [
            106.987146,
            20.992604
          ],
          [
            106.989271,
            20.992256
          ],
          [
            106.990249,
            20.992103
          ],
          [
            106.990205,
            20.992208
          ],
          [
            106.989283,
            20.992354
          ],
          [
            106.987168,
            20.992697
          ]
        ]
      }
    }
  ]
}